{
  "pcr": [
    {
      "title": "Q-GEN Series",
      "items": [
        {
          "name": "Q-GEN-5",
          "code": "Q-GEN-5",
          "has": ["spec"],
          "features": [
            {
              "title": "유연하고 통합된 분자 진단 시스템",
              "bullets": [
                "다양한 진단 키트 및 프로토콜에 대응",
                "핵산 추출부터 Real-time PCR, 결과 분석까지 하나의 장비로 모든 과정을 완결",
                "직관적이고 전문화된 장비 전용 소프트웨어 제공"
              ]
            }
          ]
        },
        {
          "name": "Q-GEN-4",
          "code": "Q-GEN-4",
          "has": ["spec"],
          "features": [
            {
              "title": "분자 진단 시스템",
              "bullets": [
                "핵산 추출부터 결과 분석까지 하나의 장비로 해결",
                "직관적인 UI"
              ]
            }
          ]
        }
      ]
    }
  ],
  "uv": [
    {
      "title": "uv",
      "items": [
        {
          "name": "에어쉴드 UV",
          "code": "AirShield-UV",
          "has": ["detail"],
          "features": [
            {
              "title": "INTRODUCTION",
              "bullets": [
                "광촉매 기술로 실내 공기를 깨끗하게 정화가능",
                "세균, 곰팡이, 악취까지 효과적으로 제거",
                "외부 환기 없이도 쾌적한 환경을 유지","작고 조용한 디자인으로 어디든 간편하게 설치 가능"
              ]
            }
          ]
        }
      ]
    }
  ]
}